hidrokit/__init__.py
hidrokit/__version__.py
hidrokit/analysis/__init__.py
hidrokit/contrib/__init__.py
hidrokit/contrib/taruma/__init__.py
hidrokit/contrib/taruma/anfrek.py
hidrokit/contrib/taruma/bmkg_utils.py
hidrokit/contrib/taruma/chi_square.py
hidrokit/contrib/taruma/dataframe_to_tensor.py
hidrokit/contrib/taruma/dependable_flow.py
hidrokit/contrib/taruma/evapotranspiration.py
hidrokit/contrib/taruma/fjmock_model.py
hidrokit/contrib/taruma/gumbel.py
hidrokit/contrib/taruma/hidrokit_excel_parser.py
hidrokit/contrib/taruma/hidrokit_hourly_excel_parser.py
hidrokit/contrib/taruma/kolmogorov_smirnov.py
hidrokit/contrib/taruma/lognormal.py
hidrokit/contrib/taruma/logpearson3.py
hidrokit/contrib/taruma/model_calibration.py
hidrokit/contrib/taruma/normal.py
hidrokit/contrib/taruma/nreca_model.py
hidrokit/contrib/taruma/outlier_hydrology.py
hidrokit/contrib/taruma/pamarayan_excel_data_extraction.py
hidrokit/contrib/taruma/statistic_summary.py
hidrokit/contrib/taruma/statistical_coefficients.py
hidrokit/contrib/taruma/summary_hourly.py
hidrokit/contrib/taruma/thiessen.py
hidrokit/contrib/taruma/ujidist.py
hidrokit/contrib/taruma/upsampling.py
hidrokit/contrib/taruma/utils.py
hidrokit/prep/__init__.py
hidrokit/prep/excel.py
hidrokit/prep/read.py
hidrokit/prep/timeseries.py
hidrokit/viz/__init__.py
hidrokit/viz/graph.py
hidrokit/viz/table.py
hidrokit-0.5.2.dist-info/LICENSE.txt
hidrokit-0.5.2.dist-info/METADATA
hidrokit-0.5.2.dist-info/WHEEL
hidrokit-0.5.2.dist-info/top_level.txt
hidrokit-0.5.2.dist-info/RECORD
