Metadata-Version: 2.1
Name: hidrokit
Version: 0.5.2
Summary: analisis hidrologi dengan python
Home-page: https://github.com/hidrokit/hidrokit
Author: Taruma Sakti Megariansyah
Author-email: hi@taruma.info
License: MIT
Project-URL: Documentation, https://hidrokit.github.io/hidrokit
Project-URL: ReadTheDocs, https://hidrokit.readthedocs.io/en/stable/
Project-URL: Bug Reports, https://github.com/hidrokit/hidrokit/issues
Project-URL: Source, https://github.com/hidrokit/hidrokit/
Classifier: Development Status :: 3 - Alpha
Classifier: Intended Audience :: Science/Research
Classifier: Topic :: Scientific/Engineering :: Hydrology
Classifier: License :: OSI Approved :: MIT License
Classifier: Programming Language :: Python
Classifier: Programming Language :: Python :: 3
Classifier: Programming Language :: Python :: 3.9
Classifier: Programming Language :: Python :: 3.10
Classifier: Programming Language :: Python :: 3.11
Requires-Python: >=3.9.0
License-File: LICENSE.txt
Requires-Dist: matplotlib >=3.7
Requires-Dist: numpy >=1.25
Requires-Dist: pandas >=2.0
Requires-Dist: scipy >=1.11
Requires-Dist: xlrd >=2.0
Provides-Extra: excel
Requires-Dist: openpyxl ; extra == 'excel'
Requires-Dist: xlrd ; extra == 'excel'
Requires-Dist: xlwt ; extra == 'excel'
